JiweiCommonUtil/__init__.py
JiweiCommonUtil/clip_amu.py
JiweiCommonUtil/clip_moco.py
JiweiCommonUtil/dataset.py
JiweiCommonUtil/datautil.py
JiweiCommonUtil/heima.py
JiweiCommonUtil/imageprocess.py
JiweiCommonUtil/imgshow.py
JiweiCommonUtil/jiweitip.py
JiweiCommonUtil/metrics.py
JiweiCommonUtil/post_proc.py
JiweiCommonUtil/stainnormalization.py
JiweiCommonUtil/tip_configs_mydataset_yaml.py
JiweiCommonUtil/tip_datasets_init_.py
JiweiCommonUtil/tip_datasets_mydataset.py
JiweiCommonUtil/tip_datasets_utils.py
JiweiCommonUtil/tip_main.py
JiweiCommonUtil/util.py
JiweiCommonUtil/Tip-Adapter/__inti__.py
JiweiCommonUtil/Tip-Adapter/main.py
JiweiCommonUtil/Tip-Adapter/main_imagenet.py
JiweiCommonUtil/Tip-Adapter/utils.py
JiweiCommonUtil-0.1.0.dist-info/LICENSE
JiweiCommonUtil-0.1.0.dist-info/METADATA
JiweiCommonUtil-0.1.0.dist-info/WHEEL
JiweiCommonUtil-0.1.0.dist-info/top_level.txt
JiweiCommonUtil-0.1.0.dist-info/RECORD
