Metadata-Version: 2.1
Name: JiweiCommonUtil
Version: 0.1.0
Summary: 自己常用的一些包，为了使用方便封装起来传到pypi
Home-page: https://github.com/JiweiMaster/jiwei_pypkg_tutorial
Author: 纪伟
Author-email: 2413914266@qq.com
Classifier: Programming Language :: Python :: 3
Classifier: License :: OSI Approved :: MIT License
Classifier: Operating System :: OS Independent
License-File: LICENSE
